minispeaker/__init__.py
minispeaker/asyncsync.py
minispeaker/devices.py
minispeaker/player.py
minispeaker/processor/convert.py
minispeaker/processor/mixer.py
minispeaker/processor/pipes.py
minispeaker/tracks.py
minispeaker-1.6.0.dist-info/WHEEL
minispeaker-1.6.0.dist-info/entry_points.txt
minispeaker-1.6.0.dist-info/METADATA
minispeaker-1.6.0.dist-info/RECORD
