Metadata-Version: 2.4
Name: minispeaker
Version: 1.6.0
Summary: Pythonic miniaudio speaker abstraction library
Keywords: sound,audio,playback,async
License-Expression: MIT
Classifier: Development Status :: 3 - Alpha
Classifier: Intended Audience :: Developers
Classifier: Typing :: Typed
Classifier: Operating System :: OS Independent
Classifier: License :: OSI Approved :: MIT License
Classifier: Programming Language :: Python :: 3.8
Classifier: Programming Language :: Python :: 3.9
Classifier: Programming Language :: Python :: 3.10
Classifier: Programming Language :: Python :: 3.11
Classifier: Programming Language :: Python :: 3.12
Classifier: Topic :: Multimedia :: Sound/Audio
Classifier: Topic :: Multimedia :: Sound/Audio :: Players
Requires-Dist: miniaudio>=1.61
Requires-Dist: numpy>=1.22.0
Requires-Dist: typing-extensions>=4.7.0
Requires-Python: >=3.8, <3.13
Project-URL: Homepage, https://github.com/agape-1/pyminispeaker/
Project-URL: Repository, https://github.com/agape-1/pyminispeaker/
